modernbutton.py
Yousra-0.0.1.dist-info/METADATA
Yousra-0.0.1.dist-info/WHEEL
Yousra-0.0.1.dist-info/top_level.txt
Yousra-0.0.1.dist-info/RECORD
