Metadata-Version: 2.1
Name: Yousra
Version: 0.0.1
Summary: بسم الله الرحمن الرحيم  والصلاة و السلام على رسول الله خير المرسلين
Author: Mahmoud Khalaf محمود خلف
Author-email: mahmoudcodetest@gmail.com
License: Copyright (c) 2023 Mahmoud Khalaf
Project-URL: Download Button Images, https://github.com/MahmoudCodetest/Button-Images
Requires-Dist: opencv-python
Requires-Dist: Pillow
